mm_neural_adjoint/__init__.py
mm_neural_adjoint/models/NA.py
mm_neural_adjoint/models/__init__.py
mm_neural_adjoint/models/conv_model.py
mm_neural_adjoint/models/lin_model.py
mm_neural_adjoint-0.1.20.dist-info/licenses/LICENSE
mm_neural_adjoint-0.1.20.dist-info/METADATA
mm_neural_adjoint-0.1.20.dist-info/WHEEL
mm_neural_adjoint-0.1.20.dist-info/top_level.txt
mm_neural_adjoint-0.1.20.dist-info/RECORD
