Metadata-Version: 2.4
Name: MM-neural-adjoint
Version: 0.1.20
Summary: A neural adjoint method implementation
Author-email: Nicholas Barsi-Rhyne <nick@quantumventura.com>
License: MIT
Keywords: neural adjoint,adjoint method,neural adjoints,meta material,deep learning
Classifier: Development Status :: 2 - Pre-Alpha
Classifier: Intended Audience :: Developers
Classifier: License :: OSI Approved :: MIT License
Classifier: Natural Language :: English
Classifier: Programming Language :: Python :: 3
Classifier: Programming Language :: Python :: 3.10
Classifier: Programming Language :: Python :: 3.11
Classifier: Programming Language :: Python :: 3.12
Requires-Python: >=3.10
License-File: LICENSE
Requires-Dist: numpy
Requires-Dist: pandas
Requires-Dist: tqdm
Requires-Dist: mlflow
Requires-Dist: scikit-learn
Requires-Dist: torch
Provides-Extra: all
Requires-Dist: groundingdino-py; extra == "all"
Dynamic: license-file
